ftml/__init__.py
ftml/exceptions.py
ftml/ftml_dict.py
ftml/logger.py
ftml/parser/__init__.py
ftml/parser/ast.py
ftml/parser/ast_visualizer.py
ftml/parser/comment_attacher.py
ftml/parser/encoding.py
ftml/parser/parser.py
ftml/parser/serializer.py
ftml/parser/tokenizer.py
ftml/schema/__init__.py
ftml/schema/schema.py
ftml/schema/schema_ast.py
ftml/schema/schema_constraint_parser.py
ftml/schema/schema_datetime_validators.py
ftml/schema/schema_debug.py
ftml/schema/schema_integration.py
ftml/schema/schema_parser.py
ftml/schema/schema_type_system.py
ftml/schema/schema_type_validators.py
ftml/schema/schema_union_parser.py
ftml/schema/schema_validator.py
ftml/version.py
ftml-0.1.0a1.dist-info/LICENSE
ftml-0.1.0a1.dist-info/METADATA
ftml-0.1.0a1.dist-info/WHEEL
ftml-0.1.0a1.dist-info/RECORD
