Metadata-Version: 2.1
Name: ftml
Version: 0.1.0a1
Summary: FTML (FlexTag Markup Language) - A human-readable data format with unified data/schema syntax. Features robust validation, type safety, rich constraints, and smart defaults. Preserves comments during round-trip processing and integrates seamlessly with Python dictionaries. Designed for both simplicity and powerful data integrity.
License: MIT
Author: DarrenHaba
Author-email: darrenhaba@live.com
Requires-Python: >=3.9
Classifier: License :: OSI Approved :: MIT License
Classifier: Programming Language :: Python :: 3
Classifier: Programming Language :: Python :: 3.9
Classifier: Programming Language :: Python :: 3.10
Classifier: Programming Language :: Python :: 3.11
Classifier: Programming Language :: Python :: 3.12
Requires-Dist: pytest (>=8.3.4,<9.0.0)
Project-URL: Bug Tracker, https://github.com/DarrenHaba/ftml/issues
Project-URL: Homepage, https://github.com/DarrenHaba/ftml
Project-URL: Repository, https://github.com/DarrenHaba/ftml
